{"cameraMode":{"drawMode":0,"name":"Shaded","section":"Shading Mode"},"sceneLighting":false,"audioPlay":false,"sceneViewState":{"showFog":true,"showMaterialUpdate":false,"showSkybox":false,"showFlares":true,"showImageEffects":true,"showParticleSystems":true},"in2DMode":false,"pivot":{"x":-1.1872683763504029,"y":-0.018617045134305955,"z":1.450671911239624},"rotation":{"x":-0.00630846805870533,"y":0.011096671223640442,"z":-0.00006287234282353893,"w":-0.9999467730522156},"size":0.8660283088684082,"orthographic":false}